metropolis/__init__.py
metropolis/gateway.py
metropolis/worker.py
metropolis/core/__init__.py
metropolis/core/driver.py
metropolis/core/executor.py
metropolis/core/serializer.py
metropolis/core/utils.py
metropolis-0.1.4.dist-info/LICENSE.md
metropolis-0.1.4.dist-info/METADATA
metropolis-0.1.4.dist-info/WHEEL
metropolis-0.1.4.dist-info/top_level.txt
metropolis-0.1.4.dist-info/RECORD
