Metadata-Version: 2.1
Name: metropolis
Version: 0.1.4
Summary: Microservice gateway using Nats
Home-page: https://github.com/ashon/metropolis
Author: ashon lee
Author-email: ashon8813@gmail.com
License: MIT
Platform: UNKNOWN
Classifier: Programming Language :: Python :: 3
Classifier: License :: OSI Approved :: MIT License
Classifier: Operating System :: OS Independent
Requires-Python: >=3
Requires-Dist: asyncio-nats-client (==0.10.0)
Requires-Dist: uvloop (==0.13.0)
Requires-Dist: sanic (==19.9.0)
